SpinSpotter/__init__.py
SpinSpotter/function_library.py
spinspotter-0.2.0.dist-info/METADATA
spinspotter-0.2.0.dist-info/WHEEL
spinspotter-0.2.0.dist-info/top_level.txt
spinspotter-0.2.0.dist-info/RECORD
