Metadata-Version: 2.1
Name: spinspotter
Version: 0.2.0
Summary: Fast, autocorrelation-based algorithm for finding stellar rotation periods from light curves.
Home-page: https://github.com/rae-holcomb/SpinSpotter
Author: Rae Holcomb
Author-email: raeholcomb15@gmail.com
License: BSD 3-clause
Platform: UNKNOWN
Classifier: Development Status :: 1 - Planning
Classifier: Intended Audience :: Science/Research
Classifier: License :: OSI Approved :: BSD License
Classifier: Operating System :: POSIX :: Linux
Classifier: Programming Language :: Python :: 3
Classifier: Programming Language :: Python :: 3.8
Requires-Dist: matplotlib
Requires-Dist: numpy
Requires-Dist: pandas
Requires-Dist: scipy
Requires-Dist: statsmodels
Requires-Dist: lightkurve (>=2.0)
